baruda/__about__.py
baruda/__init__.py
baruda/jamo_level.py
baruda/jamodict.py
baruda-0.1.3.dist-info/LICENSE
baruda-0.1.3.dist-info/METADATA
baruda-0.1.3.dist-info/WHEEL
baruda-0.1.3.dist-info/top_level.txt
baruda-0.1.3.dist-info/RECORD
