Metadata-Version: 2.1
Name: baruda
Version: 0.1.3
Summary: Fix and normalize Korean Jamo typos
Home-page: https://github.com/naubull2/baruda
Author: naubull2
Author-email: naubull2@gmail.com
Maintainer: Wooin(Dan) Lee
Maintainer-email: naubull2@gmail.com
License: BSD3
Download-URL: https://pypi.org/project/baruda/
Keywords: Korean,Hangul,Jamo
Platform: any
Classifier: Development Status :: 5 - Production/Stable
Classifier: Intended Audience :: Developers
Classifier: Intended Audience :: Science/Research
Classifier: License :: OSI Approved :: BSD License
Classifier: Natural Language :: Korean
Classifier: Operating System :: OS Independent
Classifier: Programming Language :: Python
Classifier: Programming Language :: Python :: 3.5
Classifier: Programming Language :: Python :: Implementation :: CPython
Classifier: Programming Language :: Python :: Implementation :: PyPy
Classifier: Topic :: Software Development :: Libraries :: Python Modules
Classifier: Topic :: Software Development :: Localization
Classifier: Topic :: Text Processing :: Linguistic
Requires-Dist: jamo (>=0.4.1)
